{
    "TIPO": "SIS",
    "NOMBRE": "REVS2",
    "IDENTIFICADOR": 1,
    "LECTURAS": [
        {
            "FECHA": "2025-10-29",
            "TIEMPO": "15:02:46",
            "LATITUD": -0.212183,
            "LONGITUD": -78.491557,
            "ALTURA": 2814.1,
            "ALERTA": false,
            "PASA_BANDA": "0015",
            "PASA_BAJO": "0013",
            "PASA_ALTO": "0052",
            "BATERIA": 12.47
        },
        {
            "FECHA": "2025-10-29",
            "TIEMPO": "15:07:46",
            "LATITUD": -0.212183,
            "LONGITUD": -78.491557,
            "ALTURA": 2814.1,
            "ALERTA": false,
            "PASA_BANDA": "0015",
            "PASA_BAJO": "0010",
            "PASA_ALTO": "0056",
            "BATERIA": 12.47
        },
        {
            "FECHA": "2025-10-29",
            "TIEMPO": "15:12:46",
            "LATITUD": -0.212183,
            "LONGITUD": -78.491557,
            "ALTURA": 2814.1,
            "ALERTA": false,
            "PASA_BANDA": "0018",
            "PASA_BAJO": "0013",
            "PASA_ALTO": "0055",
            "BATERIA": 12.47
        },
        {
            "FECHA": "2025-10-29",
            "TIEMPO": "15:17:46",
            "LATITUD": -0.212183,
            "LONGITUD": -78.491557,
            "ALTURA": 2814.1,
            "ALERTA": false,
            "PASA_BANDA": "0017",
            "PASA_BAJO": "0008",
            "PASA_ALTO": "0051",
            "BATERIA": 12.47
        },
        {
            "FECHA": "2025-10-29",
            "TIEMPO": "15:22:44",
            "LATITUD": -0.212183,
            "LONGITUD": -78.491557,
            "ALTURA": 2814.1,
            "ALERTA": false,
            "PASA_BANDA": "0016",
            "PASA_BAJO": "0013",
            "PASA_ALTO": "0051",
            "BATERIA": 12.47
        },
        {
            "FECHA": "2025-10-29",
            "TIEMPO": "15:27:44",
            "LATITUD": -0.212183,
            "LONGITUD": -78.491557,
            "ALTURA": 2814.1,
            "ALERTA": false,
            "PASA_BANDA": "0010",
            "PASA_BAJO": "0008",
            "PASA_ALTO": "0052",
            "BATERIA": 12.47
        },
        {
            "FECHA": "2025-10-29",
            "TIEMPO": "15:32:44",
            "LATITUD": -0.212183,
            "LONGITUD": -78.491557,
            "ALTURA": 2814.1,
            "ALERTA": false,
            "PASA_BANDA": "0012",
            "PASA_BAJO": "0008",
            "PASA_ALTO": "0051",
            "BATERIA": 12.47
        },
        {
            "FECHA": "2025-10-29",
            "TIEMPO": "15:37:44",
            "LATITUD": -0.212183,
            "LONGITUD": -78.491557,
            "ALTURA": 2814.1,
            "ALERTA": false,
            "PASA_BANDA": "0016",
            "PASA_BAJO": "0014",
            "PASA_ALTO": "0056",
            "BATERIA": 12.47
        },
        {
            "FECHA": "2025-10-29",
            "TIEMPO": "15:42:43",
            "LATITUD": -0.212183,
            "LONGITUD": -78.491557,
            "ALTURA": 2814.1,
            "ALERTA": false,
            "PASA_BANDA": "0016",
            "PASA_BAJO": "0010",
            "PASA_ALTO": "0052",
            "BATERIA": 12.47
        },
        {
            "FECHA": "2025-10-29",
            "TIEMPO": "15:47:42",
            "LATITUD": -0.212183,
            "LONGITUD": -78.491557,
            "ALTURA": 2814.1,
            "ALERTA": false,
            "PASA_BANDA": "0016",
            "PASA_BAJO": "0009",
            "PASA_ALTO": "0057",
            "BATERIA": 12.47
        },
        {
            "FECHA": "2025-10-29",
            "TIEMPO": "15:52:42",
            "LATITUD": -0.212183,
            "LONGITUD": -78.491557,
            "ALTURA": 2814.1,
            "ALERTA": false,
            "PASA_BANDA": "0012",
            "PASA_BAJO": "0008",
            "PASA_ALTO": "0051",
            "BATERIA": 12.47
        },
        {
            "FECHA": "2025-10-29",
            "TIEMPO": "15:57:42",
            "LATITUD": -0.212183,
            "LONGITUD": -78.491557,
            "ALTURA": 2814.1,
            "ALERTA": false,
            "PASA_BANDA": "0016",
            "PASA_BAJO": "0014",
            "PASA_ALTO": "0057",
            "BATERIA": 12.47
        }
    ]
}